setup.py
Ankit_distributions/Binomialdistribution.py
Ankit_distributions/Gaussiandistribution.py
Ankit_distributions/Generaldistribution.py
Ankit_distributions/__init__.py
Ankit_distributions.egg-info/PKG-INFO
Ankit_distributions.egg-info/SOURCES.txt
Ankit_distributions.egg-info/dependency_links.txt
Ankit_distributions.egg-info/not-zip-safe
Ankit_distributions.egg-info/top_level.txt